{
  "swagger": "2.0",
  "info": {
    "description": "Auto-generated API documentation",
    "version": "1.0.0",
    "title": "Generated API"
  },
  "host": "127.0.0.1:4201",
  "basePath": "/",
  "schemes": [
    "http"
  ],
  "paths": {
    "/test_get": {
      "get": {
        "summary": "Autogenerated GET method",
        "parameters": [
          {
            "name": "a1",
            "in": "query",
            "required": false,
            "type": "int",
            "schema": {
              "type": "int"
            }
          }
        ],
        "responses": {
          "200": {
            "description": "successful operation",
            "schema": {
              "$ref": "#/definitions/"
            }
          }
        }
      }
    },
    "/test_post": {
      "post": {
        "summary": "Autogenerated POST method",
        "parameters": [
          {
            "name": "body",
            "in": "body",
            "required": false,
            "type": "object",
            "schema": {
              "type": "object"
            }
          }
        ],
        "responses": {
          "200": {
            "description": "successful operation",
            "schema": {
              "$ref": "#/definitions/"
            }
          }
        }
      }
    },
    "/test_put": {
      "put": {
        "summary": "Autogenerated PUT method",
        "parameters": [
          {
            "name": "a1",
            "in": "query",
            "required": false,
            "type": "string",
            "schema": {
              "type": "string"
            }
          },
          {
            "name": "body",
            "in": "body",
            "required": false,
            "type": "object",
            "schema": {
              "type": "object"
            }
          }
        ],
        "responses": {
          "200": {
            "description": "successful operation",
            "schema": {
              "$ref": "#/definitions/"
            }
          }
        }
      }
    },
    "/test_delete": {
      "delete": {
        "summary": "Autogenerated DELETE method",
        "parameters": [
          {
            "name": "a1",
            "in": "query",
            "required": false,
            "type": "string",
            "schema": {
              "type": "string"
            }
          }
        ],
        "responses": {
          "200": {
            "description": "successful operation",
            "schema": {
              "$ref": "#/definitions/"
            }
          }
        }
      }
    },
    "/test_patch": {
      "patch": {
        "summary": "Autogenerated PATCH method",
        "parameters": [
          {
            "name": "a1",
            "in": "query",
            "required": false,
            "type": "string",
            "schema": {
              "type": "string"
            }
          },
          {
            "name": "body",
            "in": "body",
            "required": false,
            "type": "object",
            "schema": {
              "type": "object"
            }
          }
        ],
        "responses": {
          "200": {
            "description": "successful operation",
            "schema": {
              "$ref": "#/definitions/"
            }
          }
        }
      }
    },
    "/local/categorias/local/categorias/get": {
      "get": {
        "summary": "Autogenerated GET method",
        "parameters": [
          {
            "name": "id_categoria",
            "in": "query",
            "required": false,
            "type": "int",
            "schema": {
              "type": "int"
            }
          }
        ],
        "responses": {
          "200": {
            "description": "successful operation",
            "schema": {
              "$ref": "#/definitions/"
            }
          }
        }
      }
    },
    "/local/categorias/local/categorias/create": {
      "post": {
        "summary": "Autogenerated POST method",
        "parameters": [
          {
            "name": "body",
            "in": "body",
            "required": false,
            "type": "object",
            "schema": {
              "type": "object"
            }
          }
        ],
        "responses": {
          "200": {
            "description": "successful operation",
            "schema": {
              "$ref": "#/definitions/"
            }
          }
        }
      }
    },
    "/local/categorias/local/categorias/update": {
      "put": {
        "summary": "Autogenerated PUT method",
        "parameters": [
          {
            "name": "id_categoria",
            "in": "query",
            "required": false,
            "type": "int",
            "schema": {
              "type": "int"
            }
          },
          {
            "name": "body",
            "in": "body",
            "required": false,
            "type": "object",
            "schema": {
              "type": "object"
            }
          }
        ],
        "responses": {
          "200": {
            "description": "successful operation",
            "schema": {
              "$ref": "#/definitions/"
            }
          }
        }
      }
    },
    "/local/categorias/local/categorias/delete": {
      "delete": {
        "summary": "Autogenerated DELETE method",
        "parameters": [
          {
            "name": "id_categoria",
            "in": "query",
            "required": false,
            "type": "int",
            "schema": {
              "type": "int"
            }
          }
        ],
        "responses": {
          "200": {
            "description": "successful operation",
            "schema": {
              "$ref": "#/definitions/"
            }
          }
        }
      }
    },
    "/local/categorias/local/categorias/patch": {
      "patch": {
        "summary": "Autogenerated PATCH method",
        "parameters": [
          {
            "name": "id_categoria",
            "in": "query",
            "required": false,
            "type": "int",
            "schema": {
              "type": "int"
            }
          },
          {
            "name": "nombre_categoria",
            "in": "query",
            "required": false,
            "type": "string",
            "schema": {
              "type": "string"
            }
          }
        ],
        "responses": {
          "200": {
            "description": "successful operation",
            "schema": {
              "$ref": "#/definitions/"
            }
          }
        }
      }
    },
    "/local/reportes/local/reportes/get": {
      "get": {
        "summary": "Autogenerated GET method",
        "parameters": [
          {
            "name": "ID_report",
            "in": "query",
            "required": false,
            "type": "int",
            "schema": {
              "type": "int"
            }
          }
        ],
        "responses": {
          "200": {
            "description": "successful operation",
            "schema": {
              "$ref": "#/definitions/"
            }
          }
        }
      }
    },
    "/local/reportes/local/reportes/create": {
      "post": {
        "summary": "Autogenerated POST method",
        "parameters": [
          {
            "name": "body",
            "in": "body",
            "required": false,
            "type": "object",
            "schema": {
              "type": "object"
            }
          }
        ],
        "responses": {
          "200": {
            "description": "successful operation",
            "schema": {
              "$ref": "#/definitions/"
            }
          }
        }
      }
    },
    "/local/reportes/local/reportes/update": {
      "put": {
        "summary": "Autogenerated PUT method",
        "parameters": [
          {
            "name": "ID_report",
            "in": "query",
            "required": false,
            "type": "int",
            "schema": {
              "type": "int"
            }
          },
          {
            "name": "body",
            "in": "body",
            "required": false,
            "type": "object",
            "schema": {
              "type": "object"
            }
          }
        ],
        "responses": {
          "200": {
            "description": "successful operation",
            "schema": {
              "$ref": "#/definitions/"
            }
          }
        }
      }
    },
    "/local/reportes/local/reportes/delete": {
      "delete": {
        "summary": "Autogenerated DELETE method",
        "parameters": [
          {
            "name": "ID_report",
            "in": "query",
            "required": false,
            "type": "int",
            "schema": {
              "type": "int"
            }
          }
        ],
        "responses": {
          "200": {
            "description": "successful operation",
            "schema": {
              "$ref": "#/definitions/"
            }
          }
        }
      }
    },
    "/local/reportes/local/reportes/patch": {
      "patch": {
        "summary": "Autogenerated PATCH method",
        "parameters": [
          {
            "name": "ID_report",
            "in": "query",
            "required": false,
            "type": "int",
            "schema": {
              "type": "int"
            }
          },
          {
            "name": "nomReport",
            "in": "query",
            "required": false,
            "type": "string",
            "schema": {
              "type": "string"
            }
          }
        ],
        "responses": {
          "200": {
            "description": "successful operation",
            "schema": {
              "$ref": "#/definitions/"
            }
          }
        }
      }
    },
    "/local/session_tokens/local/session_tokens/get": {
      "get": {
        "summary": "Autogenerated GET method",
        "parameters": [
          {
            "name": "id_token",
            "in": "query",
            "required": false,
            "type": "int",
            "schema": {
              "type": "int"
            }
          }
        ],
        "responses": {
          "200": {
            "description": "successful operation",
            "schema": {
              "$ref": "#/definitions/"
            }
          }
        }
      }
    },
    "/local/session_tokens/local/session_tokens/create": {
      "post": {
        "summary": "Autogenerated POST method",
        "parameters": [
          {
            "name": "body",
            "in": "body",
            "required": false,
            "type": "object",
            "schema": {
              "type": "object"
            }
          }
        ],
        "responses": {
          "200": {
            "description": "successful operation",
            "schema": {
              "$ref": "#/definitions/"
            }
          }
        }
      }
    },
    "/local/session_tokens/local/session_tokens/update": {
      "put": {
        "summary": "Autogenerated PUT method",
        "parameters": [
          {
            "name": "id_token",
            "in": "query",
            "required": false,
            "type": "int",
            "schema": {
              "type": "int"
            }
          },
          {
            "name": "body",
            "in": "body",
            "required": false,
            "type": "object",
            "schema": {
              "type": "object"
            }
          }
        ],
        "responses": {
          "200": {
            "description": "successful operation",
            "schema": {
              "$ref": "#/definitions/"
            }
          }
        }
      }
    },
    "/local/session_tokens/local/session_tokens/delete": {
      "delete": {
        "summary": "Autogenerated DELETE method",
        "parameters": [
          {
            "name": "id_token",
            "in": "query",
            "required": false,
            "type": "int",
            "schema": {
              "type": "int"
            }
          }
        ],
        "responses": {
          "200": {
            "description": "successful operation",
            "schema": {
              "$ref": "#/definitions/"
            }
          }
        }
      }
    },
    "/local/session_tokens/local/session_tokens/patch": {
      "patch": {
        "summary": "Autogenerated PATCH method",
        "parameters": [
          {
            "name": "id_token",
            "in": "query",
            "required": false,
            "type": "int",
            "schema": {
              "type": "int"
            }
          },
          {
            "name": "token",
            "in": "query",
            "required": false,
            "type": "string",
            "schema": {
              "type": "string"
            }
          }
        ],
        "responses": {
          "200": {
            "description": "successful operation",
            "schema": {
              "$ref": "#/definitions/"
            }
          }
        }
      }
    },
    "/local/tokens/local/tokens/get": {
      "get": {
        "summary": "Autogenerated GET method",
        "parameters": [
          {
            "name": "id_tokens",
            "in": "query",
            "required": false,
            "type": "int",
            "schema": {
              "type": "int"
            }
          }
        ],
        "responses": {
          "200": {
            "description": "successful operation",
            "schema": {
              "$ref": "#/definitions/"
            }
          }
        }
      }
    },
    "/local/tokens/local/tokens/create": {
      "post": {
        "summary": "Autogenerated POST method",
        "parameters": [
          {
            "name": "body",
            "in": "body",
            "required": false,
            "type": "object",
            "schema": {
              "type": "object"
            }
          }
        ],
        "responses": {
          "200": {
            "description": "successful operation",
            "schema": {
              "$ref": "#/definitions/"
            }
          }
        }
      }
    },
    "/local/tokens/local/tokens/update": {
      "put": {
        "summary": "Autogenerated PUT method",
        "parameters": [
          {
            "name": "id_tokens",
            "in": "query",
            "required": false,
            "type": "int",
            "schema": {
              "type": "int"
            }
          },
          {
            "name": "body",
            "in": "body",
            "required": false,
            "type": "object",
            "schema": {
              "type": "object"
            }
          }
        ],
        "responses": {
          "200": {
            "description": "successful operation",
            "schema": {
              "$ref": "#/definitions/"
            }
          }
        }
      }
    },
    "/local/tokens/local/tokens/delete": {
      "delete": {
        "summary": "Autogenerated DELETE method",
        "parameters": [
          {
            "name": "id_tokens",
            "in": "query",
            "required": false,
            "type": "int",
            "schema": {
              "type": "int"
            }
          }
        ],
        "responses": {
          "200": {
            "description": "successful operation",
            "schema": {
              "$ref": "#/definitions/"
            }
          }
        }
      }
    },
    "/local/tokens/local/tokens/patch": {
      "patch": {
        "summary": "Autogenerated PATCH method",
        "parameters": [
          {
            "name": "id_tokens",
            "in": "query",
            "required": false,
            "type": "int",
            "schema": {
              "type": "int"
            }
          },
          {
            "name": "id_usuario",
            "in": "query",
            "required": false,
            "type": "int",
            "schema": {
              "type": "int"
            }
          }
        ],
        "responses": {
          "200": {
            "description": "successful operation",
            "schema": {
              "$ref": "#/definitions/"
            }
          }
        }
      }
    },
    "/local/usuarios/local/usuarios/get": {
      "get": {
        "summary": "Autogenerated GET method",
        "parameters": [
          {
            "name": "ID_user",
            "in": "query",
            "required": false,
            "type": "int",
            "schema": {
              "type": "int"
            }
          }
        ],
        "responses": {
          "200": {
            "description": "successful operation",
            "schema": {
              "$ref": "#/definitions/"
            }
          }
        }
      }
    },
    "/local/usuarios/local/usuarios/create": {
      "post": {
        "summary": "Autogenerated POST method",
        "parameters": [
          {
            "name": "body",
            "in": "body",
            "required": false,
            "type": "object",
            "schema": {
              "type": "object"
            }
          }
        ],
        "responses": {
          "200": {
            "description": "successful operation",
            "schema": {
              "$ref": "#/definitions/"
            }
          }
        }
      }
    },
    "/local/usuarios/local/usuarios/update": {
      "put": {
        "summary": "Autogenerated PUT method",
        "parameters": [
          {
            "name": "ID_user",
            "in": "query",
            "required": false,
            "type": "int",
            "schema": {
              "type": "int"
            }
          },
          {
            "name": "body",
            "in": "body",
            "required": false,
            "type": "object",
            "schema": {
              "type": "object"
            }
          }
        ],
        "responses": {
          "200": {
            "description": "successful operation",
            "schema": {
              "$ref": "#/definitions/"
            }
          }
        }
      }
    },
    "/local/usuarios/local/usuarios/delete": {
      "delete": {
        "summary": "Autogenerated DELETE method",
        "parameters": [
          {
            "name": "ID_user",
            "in": "query",
            "required": false,
            "type": "int",
            "schema": {
              "type": "int"
            }
          }
        ],
        "responses": {
          "200": {
            "description": "successful operation",
            "schema": {
              "$ref": "#/definitions/"
            }
          }
        }
      }
    },
    "/local/usuarios/local/usuarios/patch": {
      "patch": {
        "summary": "Autogenerated PATCH method",
        "parameters": [
          {
            "name": "ID_user",
            "in": "query",
            "required": false,
            "type": "int",
            "schema": {
              "type": "int"
            }
          },
          {
            "name": "tipoUser",
            "in": "query",
            "required": false,
            "type": "string",
            "schema": {
              "type": "string"
            }
          }
        ],
        "responses": {
          "200": {
            "description": "successful operation",
            "schema": {
              "$ref": "#/definitions/"
            }
          }
        }
      }
    }
  },
  "definitions": {
    "": {
      "type": "object",
      "properties": {}
    }
  }
}